HISTORY.rst
LICENSE
MANIFEST.in
README.rst
setup.py
collectr/__init__.py
collectr/api.py
collectr/exceptions.py
collectr/models.py
collectr/utils.py
collectr.egg-info/PKG-INFO
collectr.egg-info/SOURCES.txt
collectr.egg-info/dependency_links.txt
collectr.egg-info/requires.txt
collectr.egg-info/top_level.txt
scripts/collect_static