Metadata-Version: 1.0
Name: collectr
Version: 0.0.5
Summary: Static file management for everyone.
Home-page: http://www.lukasa.co.uk/
Author: Cory Benfield
Author-email: cory@lukasa.co.uk
License: Copyright (C) 2013 Cory Benfield
